{"name":"Dcsextract","tagline":"Extracts data from the DCS KA-50 and A-10c. A sample program is shown to see its operation. You can extract data for a cabin mounted. Only for 64 bit cpu","body":"### Comming soon for UH-1H\r\n\r\nKA50: UV26, PVI, PUI, SPU9, R800, R828\r\n\r\nA10C: CMSC, CMSP, TACAN, ILS, UHF, VHF AM, VHF FM\r\n\r\n\r\n![](https://dl.dropboxusercontent.com/s/7rkrc80a9yx7g9u/ka50find.jpg?dl=1&token_hash=AAGk7vusSqjywwSNXwUR3qvn7u3CSEhFSMOXDN7MBi5LeQ)\r\n\r\n![](https://dl.dropboxusercontent.com/s/wyzehofy2tton4g/a10cfind.jpg?dl=1&token_hash=AAFJ-5KBLHTg58B1lJ18-B8ZM5isdrBWX6TI73HEJ7w_3w)\r\n","google":"Extracts data from the DCS KA-50 and A-10c","note":"Don't delete this file! It's used internally to help with page regeneration."}